{
  "groups": [
    {
      "name": "knife4j",
      "type": "com.github.xiaoymin.knife4j.spring.configuration.Knife4jProperties",
      "sourceType": "com.github.xiaoymin.knife4j.spring.configuration.Knife4jProperties"
    }
  ],
  "properties": [
    {
      "name": "knife4j.enable",
      "type": "java.lang.Boolean",
      "description": "Whether to enable Knife4j enhanced mode",
      "defaultValue": false
    },
    {
      "name": "knife4j.basic",
      "type": "com.github.xiaoymin.knife4j.spring.configuration.Knife4jHttpBasic",
      "description": "Basic Http",
      "sourceType": "com.github.xiaoymin.knife4j.spring.configuration.Knife4jProperties"
    },{
      "name": "knife4j.basic.enable",
      "type": "java.lang.Boolean",
      "description": "Whether to enable Basic Http authentication.default false",
      "defaultValue": false
    },{
      "name": "knife4j.basic.username",
      "type": "java.lang.String",
      "description": "Basic username"
    },{
      "name": "knife4j.basic.password",
      "type": "java.lang.String",
      "description": "Basic password"
    },
    {
      "name": "knife4j.documents",
      "type": "java.util.List<com.github.xiaoymin.knife4j.core.model.MarkdownProperty>",
      "description": "other documents"
    },
    {
      "name": "knife4j.production",
      "type": "java.lang.Boolean",
      "description": "Whether to open the production environmental protection document strategy",
      "sourceType": "com.github.xiaoymin.knife4j.spring.configuration.Knife4jProperties",
      "defaultValue": false
    },
    {
      "name": "knife4j.cors",
      "type": "java.lang.Boolean",
      "description": "Whether to enable cross-domain",
      "defaultValue": false
    },
    {
      "name": "knife4j.setting",
      "type": "com.github.xiaoymin.knife4j.core.extend.OpenApiExtendSetting",
      "description": "setting",
      "sourceType": "com.github.xiaoymin.knife4j.spring.configuration.Knife4jProperties"
    },
    {
      "name": "knife4j.setting.language",
      "type": "java.lang.String",
      "description": "i18n",
      "defaultValue": "zh"
    },
    {
      "name": "knife4j.setting.enableSwaggerModels",
      "type": "java.lang.Boolean",
      "description": "Whether to display the (Swagger Models) function",
      "defaultValue": true
    },
    {
      "name": "knife4j.setting.enableDocumentManage",
      "type": "java.lang.Boolean",
      "description": "Whether to display the (document management) function",
      "defaultValue": true
    },
    {
      "name": "knife4j.setting.enableRequestCache",
      "type": "java.lang.Boolean",
      "description": "Whether to enable request parameter caching",
      "defaultValue": true
    },
    {
      "name": "knife4j.setting.enableFilterMultipartApis",
      "type": "java.lang.Boolean",
      "description": "Whether to enable filtering for the request type of @RequestMapping",
      "defaultValue": false
    },
    {
      "name": "knife4j.setting.enableFilterMultipartApiMethodType",
      "type": "java.lang.String",
      "description": "Filter request method type",
      "defaultValue": "POST"
    },
    {
      "name": "knife4j.setting.enableHost",
      "type": "java.lang.Boolean",
      "description": "Whether to enable RESTful API debugging",
      "defaultValue": false
    },
    {
      "name": "knife4j.setting.enableHostText",
      "type": "java.lang.String",
      "description": "Host Value"
    }
  ],
  "hints": [
    {
      "name": "knife4j.enable",
      "values":[
        {
          "value": true,
          "description": "Enable the use of Knife4j enhanced mode"
        },
        {
          "value": false,
          "description": "Disable Knife4j enhanced mode"
        }
      ]
    },
    {
      "name": "knife4j.basic.enable",
      "values":[
        {
          "value": true,
          "description": "Enable Basic Http authentication to protect documents"
        },
        {
          "value": false,
          "description": "Disable Basic Http authentication"
        }
      ]
    },
    {
      "name": "knife4j.production",
      "values":[
        {
          "value": true,
          "description": "Enable the production environmental protection document strategy"
        },
        {
          "value": false,
          "description": "Disable the production environmental protection document strategy"
        }
      ]
    },
    {
      "name": "knife4j.cors",
      "values":[
        {
          "value": true,
          "description": "Start a simple cross-domain configuration"
        },
        {
          "value": false,
          "description": "Disable cross-domain"
        }
      ]
    },
    {
      "name": "knife4j.setting.enableSwaggerModels",
      "values":[
        {
          "value": true,
          "description": "Display Swagger Model Functions"
        },
        {
          "value": false,
          "description": "Hidden Swagger Model Functions"
        }
      ]
    },
    {
      "name": "knife4j.setting.enableDocumentManage",
      "values":[
        {
          "value": true,
          "description": "Display DocumentManage Functions"
        },
        {
          "value": false,
          "description": "Hidden DocumentManage Functions"
        }
      ]
    },
    {
      "name": "knife4j.setting.enableRequestCache",
      "values":[
        {
          "value": true,
          "description": "Request parameters after debugging will be cached"
        },
        {
          "value": false,
          "description": "Request parameters after debugging will not be cached"
        }
      ]
    },
    {
      "name": "knife4j.setting.enableFilterMultipartApis",
      "values":[
        {
          "value": true,
          "description": "The method request type for @RequestMapping will be filtered according to the configured methodType"
        },
        {
          "value": false,
          "description": "Display all method"
        }
      ]
    },
    {
      "name": "knife4j.setting.enableHost",
      "values":[
        {
          "value": true,
          "description": "Enable Host to enable RESTful API debugging"
        },
        {
          "value": false,
          "description": "Disable RESTful API debugging"
        }
      ]
    },
    {
      "name": "knife4j.setting.language",
      "values": [
        {
          "value": "zh",
          "description": "Display Ui in Chinese"
        },
        {
          "value": "en",
          "description": "Display Ui in English"
        }
      ]
    }
  ]
}